arka_python_dev/__init__.py
arka_python_dev/api.py
tests/__init__.py
tests/test_arka.py
arka_python_dev-0.4.dist-info/LICENSE
arka_python_dev-0.4.dist-info/METADATA
arka_python_dev-0.4.dist-info/WHEEL
arka_python_dev-0.4.dist-info/top_level.txt
arka_python_dev-0.4.dist-info/RECORD
