Metadata-Version: 2.1
Name: arka_python_dev
Version: 0.4
Summary: A Python package to interact with the Arka blockchain network
Author: Python
Author-email: support@arka.com
Requires-Python: >=3.6
License-File: LICENSE
Requires-Dist: requests
Requires-Dist: tqdm
